ml_profiler/__init__.py
ml_profiler/data_summary.py
ml_profiler/explainability.py
ml_profiler/model_selector.py
ml_profiler/preprocessing_report.py
ml_profiler/report_generator.py
ml_profiler/training_evaluator.py
ml_profiler-0.3.1.dist-info/LICENSE
ml_profiler-0.3.1.dist-info/METADATA
ml_profiler-0.3.1.dist-info/WHEEL
ml_profiler-0.3.1.dist-info/top_level.txt
ml_profiler-0.3.1.dist-info/RECORD
