Metadata-Version: 2.1
Name: ml_profiler
Version: 0.3.1
Summary: Automated ML profiling and reporting tool
Author: Divyanshu Chouhan
Classifier: Programming Language :: Python :: 3
Classifier: License :: OSI Approved :: MIT License
Classifier: Operating System :: OS Independent
License-File: LICENSE
Requires-Dist: pandas
Requires-Dist: numpy
Requires-Dist: scikit-learn
Requires-Dist: matplotlib
Requires-Dist: seaborn
Requires-Dist: shap
